conan_cmake_cpp_project_tools/__init__.py
conan_cmake_cpp_project_tools/cli.py
conan_cmake_cpp_project_tools/config.py
conan_cmake_cpp_project_tools/core_utils.py
conan_cmake_cpp_project_tools/path_filter_utils.py
conan_cmake_cpp_project_tools/script.py
conan_cmake_cpp_project_tools/steps.py
conan_cmake_cpp_project_tools/utils.py
conan_cmake_cpp_project_tools-0.7.dist-info/entry_points.txt
conan_cmake_cpp_project_tools-0.7.dist-info/WHEEL
conan_cmake_cpp_project_tools-0.7.dist-info/METADATA
conan_cmake_cpp_project_tools-0.7.dist-info/RECORD
