Metadata-Version: 2.1
Name: conan-cmake-cpp-project-tools
Version: 0.7
Summary: 
Author: CD Clark III
Author-email: clifton.clark@gmail.com
Requires-Python: >=3.10,<4.0
Classifier: Programming Language :: Python :: 3
Classifier: Programming Language :: Python :: 3.10
Classifier: Programming Language :: Python :: 3.11
Requires-Dist: fspathtree (>=0.7,<0.8)
Requires-Dist: pyyaml (>=6.0,<7.0)
Requires-Dist: rich (>=12.6.0,<13.0.0)
Requires-Dist: typer (>=0.7.0,<0.8.0)
